[{"fund_name": "Tata Mid Cap Growth Fund - Direct Plan - GrowthMid Cap Fund", "stock_url": "https://www.moneycontrol.com/india/stockpricequote/banks-private-sector/idfcfirstbank/IDF01", "Stock Invested in": "IDFC First Bank Ltd.", "Sector": "Private sector bank", "Value_Mn": "958.5", "pct_of_total_holdings": "4.14%", "1m_change": "0.07%", "1Y_Highest Holding": "4.14% (Jul 2023)", "1Y_Lowest Holding": "1.31% (Aug 2022)", "Quantity": "1.10 Cr", "1M_Change_in_Qty": "0.00"}, {"fund_name": "Tata Mid Cap Growth Fund - Direct Plan - GrowthMid Cap Fund", "stock_url": "https://www.moneycontrol.com/india/stockpricequote/infrastructure-general/thermax/T", "Stock Invested in": "Thermax Ltd.", "Sector": "Heavy electrical equipment", "Value_Mn": "846.1", "pct_of_total_holdings": "3.65%", "1m_change": "0.18%", "1Y_Highest Holding": "3.82% (Mar 2023)", "1Y_Lowest Holding": "2.86% (Nov 2022)", "Quantity": "3.25 L", "1M_Change_in_Qty": "0.00"}, {"fund_name": "Tata Mid Cap Growth Fund - Direct Plan - GrowthMid Cap Fund", "stock_url": "https://www.moneycontrol.com/india/stockpricequote/banks-public-sector/indianbank/IB04", "Stock Invested in": "Indian Bank", "Sector": "Public sector bank", "Value_Mn": "735.5", "pct_of_total_holdings": "3.18%", "1m_change": "0.47%", "1Y_Highest Holding": "4.23% (Jan 2023)", "1Y_Lowest Holding": "1.46% (Aug 2022)", "Quantity": "21.20 L", "1M_Change_in_Qty": "1.37 L"}, {"fund_name": "Tata Mid Cap Growth Fund - Direct Plan - GrowthMid Cap Fund", "stock_url": "https://www.moneycontrol.com/india/stockpricequote/engines/cumminsindia/CI02", "Stock Invested in": "Cummins India Ltd.", "Sector": "Compressors, pumps & diesel engines", "Value_Mn": "694.9", "pct_of_total_holdings": "3.00%", "1m_change": "-0.20%", "1Y_Highest Holding": "3.46% (Oct 2022)", "1Y_Lowest Holding": "2.91% (Dec 2022)", "Quantity": "3.53 L", "1M_Change_in_Qty": "0.00"}, {"fund_name": "Tata Mid Cap Growth Fund - Direct Plan - GrowthMid Cap Fund", "stock_url": "https://www.moneycontrol.com/india/stockpricequote/castings-forgings/aiaengineering/AIE01", "Stock Invested in": "AIA Engineering Ltd.", "Sector": "Castings & forgings", "Value_Mn": "691.7", "pct_of_total_holdings": "2.99%", "1m_change": "0.00%", "1Y_Highest Holding": "3.75% (May 2023)", "1Y_Lowest Holding": "1.88% (Sep 2022)", "Quantity": "2.00 L", "1M_Change_in_Qty": "0.00"}, {"fund_name": "Tata Mid Cap Growth Fund - Direct Plan - GrowthMid Cap Fund", "stock_url": "https://www.moneycontrol.com/india/stockpricequote/pesticides-agro-chemicals/piindustries/PII", "Stock Invested in": "Pi Industries Ltd.", "Sector": "Pesticides & agrochemicals", "Value_Mn": "674", "pct_of_total_holdings": "2.91%", "1m_change": "-0.50%", "1Y_Highest Holding": "3.41% (Jun 2023)", "1Y_Lowest Holding": "2.55% (Sep 2022)", "Quantity": "1.86 L", "1M_Change_in_Qty": "0.00"}, {"fund_name": "Tata Mid Cap Growth Fund - Direct Plan - GrowthMid Cap Fund", "stock_url": "https://www.moneycontrol.com/india/stockpricequote/ceramics-granite/kajariaceramics/KC06", "Stock Invested in": "Kajaria Ceramics Ltd.", "Sector": "Ceramics", "Value_Mn": "667.9", "pct_of_total_holdings": "2.89%", "1m_change": "0.16%", "1Y_Highest Holding": "2.93% (May 2023)", "1Y_Lowest Holding": "1.02% (Aug 2022)", "Quantity": "4.65 L", "1M_Change_in_Qty": "0.00"}, {"fund_name": "Tata Mid Cap Growth Fund - Direct Plan - GrowthMid Cap Fund", "stock_url": "https://www.moneycontrol.com/india/stockpricequote/pharmaceuticals/aurobindopharma/AP", "Stock Invested in": "Aurobindo Pharma Ltd.", "Sector": "Pharmaceuticals", "Value_Mn": "666", "pct_of_total_holdings": "2.88%", "1m_change": "0.50%", "1Y_Highest Holding": "2.88% (Jul 2023)", "1Y_Lowest Holding": "0% (Aug 2022)", "Quantity": "8.10 L", "1M_Change_in_Qty": "1.10 L"}, {"fund_name": "Tata Mid Cap Growth Fund - Direct Plan - GrowthMid Cap Fund", "stock_url": "https://www.moneycontrol.com/india/stockpricequote/finance-nbfc/creditaccessgrameen/CG03", "Stock Invested in": "CreditAccess Grameen Ltd.", "Sector": "Microfinance institutions", "Value_Mn": "568.7", "pct_of_total_holdings": "2.46%", "1m_change": "0.19%", "1Y_Highest Holding": "2.46% (Jul 2023)", "1Y_Lowest Holding": "0% (Aug 2022)", "Quantity": "3.91 L", "1M_Change_in_Qty": "0.00"}, {"fund_name": "Tata Mid Cap Growth Fund - Direct Plan - GrowthMid Cap Fund", "stock_url": "https://www.moneycontrol.com/india/stockpricequote/steel-tubes-pipes/aplapollotubes/BT09", "Stock Invested in": "APL Apollo Tubes Ltd.", "Sector": "Iron & steel products", "Value_Mn": "481.3", "pct_of_total_holdings": "2.08%", "1m_change": "0.24%", "1Y_Highest Holding": "2.08% (Jul 2023)", "1Y_Lowest Holding": "0% (Aug 2022)", "Quantity": "3.02 L", "1M_Change_in_Qty": "0.00"}]